aiohttp_index/__init__.py
aiohttp_index/index.py
aiohttp_index-0.1.dist-info/DESCRIPTION.rst
aiohttp_index-0.1.dist-info/METADATA
aiohttp_index-0.1.dist-info/RECORD
aiohttp_index-0.1.dist-info/WHEEL
aiohttp_index-0.1.dist-info/metadata.json
aiohttp_index-0.1.dist-info/top_level.txt
