Metadata-Version: 1.1
Name: aiohttp-index
Version: 0.1
Summary: aiohttp.web middleware to serve index files (e.g. index.html) when static directories are requested.
Home-page: https://github.com/crowsonkb/aiohttp_index
Author: Katherine Crowson
Author-email: crowsonkb@gmail.com
License: MIT
Keywords: asyncio aiohttp
Platform: UNKNOWN
Classifier: Development Status :: 3 - Alpha
Classifier: Intended Audience :: Developers
Classifier: Topic :: Internet :: WWW/HTTP
Classifier: License :: OSI Approved :: MIT License
Classifier: Programming Language :: Python :: 3
Classifier: Programming Language :: Python :: 3.5
